page_scoop/__main__.py
page_scoop-0.1.2.dist-info/METADATA
page_scoop-0.1.2.dist-info/WHEEL
page_scoop-0.1.2.dist-info/entry_points.txt
page_scoop-0.1.2.dist-info/RECORD
