Metadata-Version: 2.4
Name: page-scoop
Version: 0.1.2
Summary: A simple tool to scoop up HTML and screenshots from web pages using a browserless instance secured by CF Zero Access
Author-email: Adam McKay <adam@beepboop.digital>
Requires-Python: >=3.10
Requires-Dist: click==8.1.8
Requires-Dist: httpx>=0.28.1
Requires-Dist: pydantic>=2.11.4
Requires-Dist: rich>=14.0.0
Requires-Dist: typer>=0.15.3
